apropos/__init__.py
apropos/goldminer/__init__.py
apropos/goldminer/output/__init__.py
apropos/goldminer/output/goldCurses.py
apropos/goldminer/output/goldFsdb.py
apropos/goldminer/output/goldHighLowWatermark.py
apropos/goldminer/output/goldJson.py
apropos/goldminer/output/goldOutput.py
apropos/goldminer/output/goldTextDump.py
apropos/goldminer/output/noop.py
apropos/goldminer/pickaxe/__init__.py
apropos/goldminer/pickaxe/pickaxe.py
apropos/goldminer/reports/__init__.py
apropos/goldminer/tests/__init__.py
apropos/goldminer/tests/test_loads.py
apropos/goldminer/tests/test_pickaxe_math.py
apropos/goldminer/tools/__init__.py
apropos/goldminer/tools/aggregator.py
apropos/goldminer/tools/goldminer.py
apropos/goldminer/tools/smelter.py
apropos/goldminer/tools/trainer.py
apropos/goldminer/trainer/__init__.py
apropos/goldminer/trainer/widthtrainer.py
gold_miner-1.2.dist-info/LICENSE
gold_miner-1.2.dist-info/METADATA
gold_miner-1.2.dist-info/WHEEL
gold_miner-1.2.dist-info/entry_points.txt
gold_miner-1.2.dist-info/top_level.txt
gold_miner-1.2.dist-info/RECORD
