Metadata-Version: 2.1
Name: gold-miner
Version: 1.2
Summary: A encrypted tunnel identification research package
Home-page: https://gitlab.com/isi-apropos/gold-miner
Author: Wes Hardaker
Author-email: opensource@hardakers.net
Classifier: Programming Language :: Python :: 3
Classifier: Operating System :: OS Independent
Requires-Python: >=3.6
License-File: LICENSE
Requires-Dist: pyfsdb
Requires-Dist: numpy
Requires-Dist: dpkt
Requires-Dist: rich
Requires-Dist: pyaml
